[
    [
        {
            "speaker" : "???",
            "dialog" : "Hey you, stop sleeping! The game’s not over, you know.",
            "newSpeaker" : "true"
        },
  {
            "speaker" : "???",
            "dialog" : "HEY WAKE UP! THIS ISN’T A GAME OVER SCREEN, YOU IMBECILE!",
            "newSpeaker" : "true"
        },
  {
            "speaker" : "???",
            "dialog" : "I’m sorry, that was too harsh. Let’s try this again. (Ahem)",
            "newSpeaker" : "true"
        },
  {
            "speaker" : "???",
            "dialog" : "Dearest traveler from a land much more HD, it is not time for you to perish. Not yet.",
            "newSpeaker" : "true"
        },
  {
            "speaker" : "???",
            "dialog" : "You still have a stage to finish! Now go, return back to your friends, oh young stretchy cat!",
            "newSpeaker" : "true"
        }

    ]
]
