{"frames":{"dig_1":{"frame":{"x":266,"y":554,"w":265,"h":324},"rotated":false,"trimmed":false,"spriteSourceSize":{"x":0,"y":0,"w":265,"h":324},"sourceSize":{"w":265,"h":324}},"dig_2":{"frame":{"x":0,"y":229,"w":265,"h":324},"rotated":false,"trimmed":false,"spriteSourceSize":{"x":0,"y":0,"w":265,"h":324},"sourceSize":{"w":265,"h":324}},"dig_3":{"frame":{"x":532,"y":554,"w":265,"h":324},"rotated":false,"trimmed":false,"spriteSourceSize":{"x":0,"y":0,"w":265,"h":324},"sourceSize":{"w":265,"h":324}},"dig_4":{"frame":{"x":0,"y":554,"w":265,"h":324},"rotated":false,"trimmed":false,"spriteSourceSize":{"x":0,"y":0,"w":265,"h":324},"sourceSize":{"w":265,"h":324}},"mole_walk1":{"frame":{"x":266,"y":0,"w":269,"h":332},"rotated":false,"trimmed":false,"spriteSourceSize":{"x":0,"y":0,"w":269,"h":332},"sourceSize":{"w":269,"h":332}},"mole_walk2":{"frame":{"x":536,"y":0,"w":269,"h":332},"rotated":false,"trimmed":false,"spriteSourceSize":{"x":0,"y":0,"w":269,"h":332},"sourceSize":{"w":269,"h":332}},"shitty_mole":{"frame":{"x":0,"y":0,"w":264,"h":228},"rotated":false,"trimmed":false,"spriteSourceSize":{"x":0,"y":0,"w":264,"h":228},"sourceSize":{"w":264,"h":228}}},"meta":{"app":"https://www.leshylabs.com/apps/sstool/","version":"Leshy SpriteSheet Tool v0.8.4","image":"mole.png","size":{"w":805,"h":878},"scale":1}}